koji/__init__.py
koji/_version.py
koji/arch.py
koji/context.py
koji/daemon.py
koji/plugin.py
koji/policy.py
koji/rpmdiff.py
koji/server.py
koji/tasks.py
koji/util.py
koji/xmlrpcplus.py
koji-1.35.3.data/scripts/koji
koji-1.35.3.data/scripts/koji-gc
koji-1.35.3.data/scripts/koji-shadow
koji-1.35.3.data/scripts/koji-sweep-db
koji-1.35.3.data/scripts/kojira
koji_cli/__init__.py
koji_cli/commands.py
koji_cli/lib.py
koji_cli_plugins/dud.py
koji_cli_plugins/kiwi.py
koji_cli_plugins/runroot.py
koji_cli_plugins/save_failed_tree.py
koji_cli_plugins/sidetag_cli.py
koji-1.35.3.dist-info/COPYING
koji-1.35.3.dist-info/METADATA
koji-1.35.3.dist-info/WHEEL
koji-1.35.3.dist-info/top_level.txt
koji-1.35.3.dist-info/RECORD
