Metadata-Version: 2.1
Name: koji
Version: 1.35.3
Summary: Koji is a system for building and tracking RPMS. The base package contains shared libraries and the command-line interface.
Home-page: http://pagure.io/koji/
Author: Koji developers
Author-email: koji-devel@lists.fedorahosted.org
License: LGPLv2 and GPLv2+
Platform: UNKNOWN
Classifier: Development Status :: 5 - Production/Stable
Classifier: Environment :: Console
Classifier: Intended Audience :: Developers
Classifier: License :: OSI Approved :: GNU Lesser General Public License v2 or later (LGPLv2+)
Classifier: Natural Language :: English
Classifier: Programming Language :: Python :: 2.7
Classifier: Programming Language :: Python :: 3
Classifier: Operating System :: POSIX :: Linux
Classifier: Topic :: Utilities
Requires-Python: >=2.7
Requires-Dist: defusedxml
Requires-Dist: python-dateutil
Requires-Dist: requests
Requires-Dist: requests-gssapi
Requires-Dist: six
